{
   "cam_type": "sensor.camera.rgb",
   "cam_id": 391,
   "cam_location": {
      "x": 228.00404357910156,
      "y": -374.9236145019531,
      "z": 3.0829005241394043
   },
   "cam_rotation": {
      "roll": -0.0009765624417923391,
      "pitch": -0.39983925223350525,
      "yaw": -0.32232666015625
   },
   "img_name": "518.png",
   "img_width": 640,
   "img_height": 680,
   "img_fov": 100,
   "debug_info": [
      {
         "actor_type": "vehicle.audi.etron",
         "actor_id": 334,
         "actor_location": {
            "x": 238.90716552734375,
            "y": -364.2121276855469,
            "z": -0.04824642091989517
         },
         "actor_rotation": {
            "roll": 0.0014276710571721196,
            "pitch": 0.04216275364160538,
            "yaw": -0.532073974609375
         },
         "actor_bbox_ext": {
            "x": 2.4270286560058594,
            "y": 1.0045700073242188,
            "z": 0.8343994617462158
         }
      },
      {
         "actor_type": "vehicle.bmw.grandtourer",
         "actor_id": 335,
         "actor_location": {
            "x": 240.498046875,
            "y": -367.6829528808594,
            "z": 0.07022231817245483
         },
         "actor_rotation": {
            "roll": -0.0010070803109556437,
            "pitch": 0.38401371240615845,
            "yaw": -0.262786865234375
         },
         "actor_bbox_ext": {
            "x": 2.3195438385009766,
            "y": 1.129660964012146,
            "z": 0.8390889763832092
         }
      },
      {
         "actor_type": "vehicle.bmw.grandtourer",
         "actor_id": 336,
         "actor_location": {
            "x": 208.782958984375,
            "y": -385.25189208984375,
            "z": 0.07191913574934006
         },
         "actor_rotation": {
            "roll": 0.0028417035937309265,
            "pitch": 0.2317141592502594,
            "yaw": -179.59255981445312
         },
         "actor_bbox_ext": {
            "x": 2.3195438385009766,
            "y": 1.129660964012146,
            "z": 0.8390889763832092
         }
      },
      {
         "actor_type": "vehicle.chevrolet.impala",
         "actor_id": 337,
         "actor_location": {
            "x": 207.31759643554688,
            "y": -388.76025390625,
            "z": -0.048730771988630295
         },
         "actor_rotation": {
            "roll": 0.0005223220796324313,
            "pitch": 0.12566182017326355,
            "yaw": -179.59385681152344
         },
         "actor_bbox_ext": {
            "x": 2.684596538543701,
            "y": 1.026368260383606,
            "z": 0.7075497508049011
         }
      },
      {
         "actor_type": "vehicle.dodge_charger.police",
         "actor_id": 338,
         "actor_location": {
            "x": 208.144287109375,
            "y": -392.25640869140625,
            "z": -0.017679957672953606
         },
         "actor_rotation": {
            "roll": -0.0016479487530887127,
            "pitch": 0.06976354867219925,
            "yaw": -179.59251403808594
         },
         "actor_bbox_ext": {
            "x": 2.4965829849243164,
            "y": 1.0679636001586914,
            "z": 0.7898477911949158
         }
      },
      {
         "actor_type": "vehicle.harley-davidson.low rider",
         "actor_id": 339,
         "actor_location": {
            "x": 211.27552795410156,
            "y": -395.74041748046875,
            "z": -0.030346106737852097
         },
         "actor_rotation": {
            "roll": 6.347423186525702e-05,
            "pitch": -0.2627232074737549,
            "yaw": -179.52012634277344
         },
         "actor_bbox_ext": {
            "x": 1.175087809562683,
            "y": 0.3831165134906769,
            "z": 0.7318695783615112
         }
      },
      {
         "actor_type": "vehicle.kawasaki.ninja",
         "actor_id": 340,
         "actor_location": {
            "x": 253.36126708984375,
            "y": -384.9293212890625,
            "z": 0.005195255391299725
         },
         "actor_rotation": {
            "roll": 2.5236033252440393e-05,
            "pitch": 0.43507620692253113,
            "yaw": -179.45420837402344
         },
         "actor_bbox_ext": {
            "x": 1.021842122077942,
            "y": 0.3984561562538147,
            "z": 0.687301516532898
         }
      },
      {
         "actor_type": "vehicle.yamaha.yzf",
         "actor_id": 341,
         "actor_location": {
            "x": 254.7279510498047,
            "y": -388.4031677246094,
            "z": -0.03777683153748512
         },
         "actor_rotation": {
            "roll": -1.0422211010885363e-10,
            "pitch": -0.3268723487854004,
            "yaw": -179.57077026367188
         },
         "actor_bbox_ext": {
            "x": 1.0953842401504517,
            "y": 0.3831165134906769,
            "z": 0.8172529339790344
         }
      },
      {
         "actor_type": "vehicle.toyota.prius",
         "actor_id": 342,
         "actor_location": {
            "x": 252.6780548095703,
            "y": -391.9244384765625,
            "z": 0.03635890781879425
         },
         "actor_rotation": {
            "roll": -0.00012207032705191523,
            "pitch": -0.007936679758131504,
            "yaw": -179.5384521484375
         },
         "actor_bbox_ext": {
            "x": 2.2691667079925537,
            "y": 1.0005652904510498,
            "z": 0.7686808109283447
         }
      },
      {
         "actor_type": "vehicle.yamaha.yzf",
         "actor_id": 343,
         "actor_location": {
            "x": 255.33270263671875,
            "y": -395.3996887207031,
            "z": -0.039352551102638245
         },
         "actor_rotation": {
            "roll": -3.0517488994519226e-05,
            "pitch": -0.4921492636203766,
            "yaw": -179.5705108642578
         },
         "actor_bbox_ext": {
            "x": 1.0953842401504517,
            "y": 0.3831165134906769,
            "z": 0.8172529339790344
         }
      },
      {
         "actor_type": "vehicle.toyota.prius",
         "actor_id": 344,
         "actor_location": {
            "x": 191.38368225097656,
            "y": -367.87542724609375,
            "z": 0.03475356847047806
         },
         "actor_rotation": {
            "roll": -0.0010375974234193563,
            "pitch": 0.14091362059116364,
            "yaw": 0.4778587818145752
         },
         "actor_bbox_ext": {
            "x": 2.2691667079925537,
            "y": 1.0005652904510498,
            "z": 0.7686808109283447
         }
      },
      {
         "actor_type": "vehicle.mini.cooperst",
         "actor_id": 345,
         "actor_location": {
            "x": 191.68161010742188,
            "y": -371.3814392089844,
            "z": 0.04387397691607475
         },
         "actor_rotation": {
            "roll": -0.0007934569730423391,
            "pitch": -0.25799670815467834,
            "yaw": 0.40024927258491516
         },
         "actor_bbox_ext": {
            "x": 1.9010963439941406,
            "y": 0.9870172142982483,
            "z": 0.7375003099441528
         }
      },
      {
         "actor_type": "vehicle.lincoln.mkz2017",
         "actor_id": 346,
         "actor_location": {
            "x": 189.3981170654297,
            "y": -374.8944396972656,
            "z": -0.006801452487707138
         },
         "actor_rotation": {
            "roll": 0.0003420103166718036,
            "pitch": -0.3521098792552948,
            "yaw": 0.4355534613132477
         },
         "actor_bbox_ext": {
            "x": 2.4543750286102295,
            "y": 1.056093692779541,
            "z": 0.7615917921066284
         }
      },
      {
         "actor_type": "vehicle.chevrolet.impala",
         "actor_id": 347,
         "actor_location": {
            "x": 234.63853454589844,
            "y": -371.1569519042969,
            "z": -0.05002475529909134
         },
         "actor_rotation": {
            "roll": -0.0008239744929596782,
            "pitch": 0.24710939824581146,
            "yaw": -0.28280630707740784
         },
         "actor_bbox_ext": {
            "x": 2.684596538543701,
            "y": 1.026368260383606,
            "z": 0.7075497508049011
         }
      },
      {
         "actor_type": "vehicle.mini.cooperst",
         "actor_id": 348,
         "actor_location": {
            "x": 233.48455810546875,
            "y": -374.6544189453125,
            "z": 0.04459720477461815
         },
         "actor_rotation": {
            "roll": -0.0009765624417923391,
            "pitch": -0.39983925223350525,
            "yaw": -0.32232666015625
         },
         "actor_bbox_ext": {
            "x": 1.9010963439941406,
            "y": 0.9870172142982483,
            "z": 0.7375003099441528
         }
      },
      {
         "actor_type": "walker.pedestrian.0013",
         "actor_id": 349,
         "actor_location": {
            "x": 338.9387512207031,
            "y": -165.10142517089844,
            "z": 1.0197923183441162
         },
         "actor_rotation": {
            "roll": 0.0,
            "pitch": 0.0,
            "yaw": 28.793262481689453
         },
         "actor_bbox_ext": {
            "x": 0.3400000035762787,
            "y": 0.3400000035762787,
            "z": 0.6499999761581421
         }
      },
      {
         "actor_type": "walker.pedestrian.0008",
         "actor_id": 350,
         "actor_location": {
            "x": 251.21603393554688,
            "y": -206.34983825683594,
            "z": 1.123484492301941
         },
         "actor_rotation": {
            "roll": 0.0,
            "pitch": 0.0,
            "yaw": -134.06590270996094
         },
         "actor_bbox_ext": {
            "x": 0.3400000035762787,
            "y": 0.3400000035762787,
            "z": 0.9300000071525574
         }
      },
      {
         "actor_type": "walker.pedestrian.0010",
         "actor_id": 351,
         "actor_location": {
            "x": 52.79229736328125,
            "y": -190.27804565429688,
            "z": 0.7522268295288086
         },
         "actor_rotation": {
            "roll": 0.0,
            "pitch": 0.0,
            "yaw": -165.1801300048828
         },
         "actor_bbox_ext": {
            "x": 0.25,
            "y": 0.25,
            "z": 0.550000011920929
         }
      },
      {
         "actor_type": "walker.pedestrian.0008",
         "actor_id": 352,
         "actor_location": {
            "x": 341.37213134765625,
            "y": -126.63720703125,
            "z": 1.1217924356460571
         },
         "actor_rotation": {
            "roll": 0.0,
            "pitch": 0.0,
            "yaw": -91.99535369873047
         },
         "actor_bbox_ext": {
            "x": 0.3400000035762787,
            "y": 0.3400000035762787,
            "z": 0.9300000071525574
         }
      },
      {
         "actor_type": "walker.pedestrian.0014",
         "actor_id": 353,
         "actor_location": {
            "x": 252.4312286376953,
            "y": -279.3752136230469,
            "z": 0.8434844613075256
         },
         "actor_rotation": {
            "roll": 0.0,
            "pitch": 0.0,
            "yaw": 169.68759155273438
         },
         "actor_bbox_ext": {
            "x": 0.3400000035762787,
            "y": 0.3400000035762787,
            "z": 0.6499999761581421
         }
      },
      {
         "actor_type": "walker.pedestrian.0012",
         "actor_id": 354,
         "actor_location": {
            "x": 174.9573974609375,
            "y": -302.1687927246094,
            "z": 0.8575608134269714
         },
         "actor_rotation": {
            "roll": 0.0,
            "pitch": 0.0,
            "yaw": -28.818695068359375
         },
         "actor_bbox_ext": {
            "x": 0.3400000035762787,
            "y": 0.3400000035762787,
            "z": 0.6499999761581421
         }
      },
      {
         "actor_type": "walker.pedestrian.0002",
         "actor_id": 355,
         "actor_location": {
            "x": 213.5429229736328,
            "y": -242.43104553222656,
            "z": 1.1082333326339722
         },
         "actor_rotation": {
            "roll": 0.0,
            "pitch": 0.0,
            "yaw": 27.051891326904297
         },
         "actor_bbox_ext": {
            "x": 0.3400000035762787,
            "y": 0.3400000035762787,
            "z": 0.9300000071525574
         }
      },
      {
         "actor_type": "walker.pedestrian.0006",
         "actor_id": 356,
         "actor_location": {
            "x": 238.3417510986328,
            "y": -126.70252990722656,
            "z": 1.1234921216964722
         },
         "actor_rotation": {
            "roll": 0.0,
            "pitch": 0.0,
            "yaw": 1.345991849899292
         },
         "actor_bbox_ext": {
            "x": 0.3400000035762787,
            "y": 0.3400000035762787,
            "z": 0.9300000071525574
         }
      },
      {
         "actor_type": "walker.pedestrian.0011",
         "actor_id": 357,
         "actor_location": {
            "x": 291.6640319824219,
            "y": -242.28811645507812,
            "z": 0.7282334566116333
         },
         "actor_rotation": {
            "roll": 0.0,
            "pitch": 0.0,
            "yaw": -25.42264747619629
         },
         "actor_bbox_ext": {
            "x": 0.25,
            "y": 0.25,
            "z": 0.550000011920929
         }
      },
      {
         "actor_type": "walker.pedestrian.0010",
         "actor_id": 358,
         "actor_location": {
            "x": 262.9357604980469,
            "y": -177.0573272705078,
            "z": 0.9148465991020203
         },
         "actor_rotation": {
            "roll": 0.0,
            "pitch": 0.0,
            "yaw": -33.83818054199219
         },
         "actor_bbox_ext": {
            "x": 0.25,
            "y": 0.25,
            "z": 0.550000011920929
         }
      },
      {
         "actor_type": "walker.pedestrian.0006",
         "actor_id": 359,
         "actor_location": {
            "x": 262.58892822265625,
            "y": -193.48524475097656,
            "z": 1.123484492301941
         },
         "actor_rotation": {
            "roll": 0.0,
            "pitch": 0.0,
            "yaw": 168.4287872314453
         },
         "actor_bbox_ext": {
            "x": 0.3400000035762787,
            "y": 0.3400000035762787,
            "z": 0.9300000071525574
         }
      },
      {
         "actor_type": "walker.pedestrian.0012",
         "actor_id": 360,
         "actor_location": {
            "x": 250.9569854736328,
            "y": -294.1861877441406,
            "z": 0.8434844613075256
         },
         "actor_rotation": {
            "roll": 0.0,
            "pitch": 0.0,
            "yaw": -153.15989685058594
         },
         "actor_bbox_ext": {
            "x": 0.3400000035762787,
            "y": 0.3400000035762787,
            "z": 0.6499999761581421
         }
      },
      {
         "actor_type": "walker.pedestrian.0013",
         "actor_id": 361,
         "actor_location": {
            "x": 251.03732299804688,
            "y": -208.57098388671875,
            "z": 0.8434844613075256
         },
         "actor_rotation": {
            "roll": 0.0,
            "pitch": 0.0,
            "yaw": 158.83450317382812
         },
         "actor_bbox_ext": {
            "x": 0.3400000035762787,
            "y": 0.3400000035762787,
            "z": 0.6499999761581421
         }
      },
      {
         "actor_type": "walker.pedestrian.0006",
         "actor_id": 362,
         "actor_location": {
            "x": 328.3182678222656,
            "y": -205.0889434814453,
            "z": 0.9558438658714294
         },
         "actor_rotation": {
            "roll": 0.0,
            "pitch": 0.0,
            "yaw": -170.0666961669922
         },
         "actor_bbox_ext": {
            "x": 0.3400000035762787,
            "y": 0.3400000035762787,
            "z": 0.9300000071525574
         }
      },
      {
         "actor_type": "walker.pedestrian.0011",
         "actor_id": 363,
         "actor_location": {
            "x": 72.91181182861328,
            "y": -268.11517333984375,
            "z": 0.7522268295288086
         },
         "actor_rotation": {
            "roll": 0.0,
            "pitch": 0.0,
            "yaw": -94.25701904296875
         },
         "actor_bbox_ext": {
            "x": 0.25,
            "y": 0.25,
            "z": 0.550000011920929
         }
      },
      {
         "actor_type": "walker.pedestrian.0012",
         "actor_id": 364,
         "actor_location": {
            "x": 104.05162811279297,
            "y": -179.585205078125,
            "z": 1.0197921991348267
         },
         "actor_rotation": {
            "roll": 0.0,
            "pitch": 0.0,
            "yaw": 3.6213431358337402
         },
         "actor_bbox_ext": {
            "x": 0.3400000035762787,
            "y": 0.3400000035762787,
            "z": 0.6499999761581421
         }
      },
      {
         "actor_type": "walker.pedestrian.0014",
         "actor_id": 365,
         "actor_location": {
            "x": 52.82767105102539,
            "y": -197.74493408203125,
            "z": 0.8522268533706665
         },
         "actor_rotation": {
            "roll": 0.0,
            "pitch": 0.0,
            "yaw": -161.523193359375
         },
         "actor_bbox_ext": {
            "x": 0.3400000035762787,
            "y": 0.3400000035762787,
            "z": 0.6499999761581421
         }
      },
      {
         "actor_type": "walker.pedestrian.0012",
         "actor_id": 366,
         "actor_location": {
            "x": 218.49618530273438,
            "y": -176.36065673828125,
            "z": 1.0197923183441162
         },
         "actor_rotation": {
            "roll": 0.0,
            "pitch": 0.0,
            "yaw": 34.03860855102539
         },
         "actor_bbox_ext": {
            "x": 0.3400000035762787,
            "y": 0.3400000035762787,
            "z": 0.6499999761581421
         }
      },
      {
         "actor_type": "walker.pedestrian.0009",
         "actor_id": 367,
         "actor_location": {
            "x": 227.11630249023438,
            "y": -304.4031066894531,
            "z": 0.7281650900840759
         },
         "actor_rotation": {
            "roll": 0.0,
            "pitch": 0.0,
            "yaw": 5.131881237030029
         },
         "actor_bbox_ext": {
            "x": 0.25,
            "y": 0.25,
            "z": 0.550000011920929
         }
      },
      {
         "actor_type": "walker.pedestrian.0009",
         "actor_id": 368,
         "actor_location": {
            "x": 221.77413940429688,
            "y": -165.62460327148438,
            "z": 0.9197922945022583
         },
         "actor_rotation": {
            "roll": 0.0,
            "pitch": 0.0,
            "yaw": -3.4982001781463623
         },
         "actor_bbox_ext": {
            "x": 0.25,
            "y": 0.25,
            "z": 0.550000011920929
         }
      },
      {
         "actor_type": "walker.pedestrian.0011",
         "actor_id": 369,
         "actor_location": {
            "x": 340.95611572265625,
            "y": -164.44219970703125,
            "z": 0.9197922945022583
         },
         "actor_rotation": {
            "roll": 0.0,
            "pitch": 0.0,
            "yaw": -26.206403732299805
         },
         "actor_bbox_ext": {
            "x": 0.25,
            "y": 0.25,
            "z": 0.550000011920929
         }
      }
   ]
}