{
    "number_of_walkers": 2,
    "vehicles": [
        {
            "min_x": 586,
            "min_y": 424,
            "max_y": 681,
            "max_x": 693
        },
        {
            "min_x": 7,
            "min_y": 373,
            "max_y": 435,
            "max_x": 136
        },
        {
            "min_x": 944,
            "min_y": 327,
            "max_y": 375,
            "max_x": 1107
        }
    ],
    "number_of_vehicles": 3,
    "walkers": [
        {
            "min_x": 923,
            "min_y": 330,
            "max_y": 361,
            "max_x": 947
        },
        {
            "min_x": 1135,
            "min_y": 326,
            "max_y": 352,
            "max_x": 1159
        }
    ]
}