{
   "image_name": "226.png",
   "object_1": {
      "class": "vehicle",
      "identify": [
         {
            "P0": 367,
            "P1": 225,
            "P2": 592,
            "P3": 468
         },
         {
            "P0": 431,
            "P1": 142,
            "P2": 440,
            "P3": 145
         },
         {
            "P0": 428,
            "P1": 142,
            "P2": 436,
            "P3": 145
         },
         {
            "P0": 467,
            "P1": 141,
            "P2": 475,
            "P3": 145
         },
         {
            "P0": 463,
            "P1": 142,
            "P2": 466,
            "P3": 145
         },
         {
            "P0": 737,
            "P1": -379,
            "P2": 1244,
            "P3": 0
         },
         {
            "P0": 717,
            "P1": 142,
            "P2": 764,
            "P3": 160
         },
         {
            "P0": 1256,
            "P1": 150,
            "P2": 1284,
            "P3": 160
         }
      ]
   },
   "object_2": {
      "class": "pedestrian",
      "identify": [
         {
            "P0": 842,
            "P1": 163,
            "P2": 881,
            "P3": 212
         },
         {
            "P0": 276,
            "P1": 149,
            "P2": 280,
            "P3": 155
         },
         {
            "P0": 268,
            "P1": 141,
            "P2": 271,
            "P3": 146
         },
         {
            "P0": 620,
            "P1": 153,
            "P2": 629,
            "P3": 167
         },
         {
            "P0": 3777,
            "P1": 158,
            "P2": 3975,
            "P3": 202
         }
      ]
   }
}