{
   "image_name": "318.png",
   "object_1": {
      "class": "vehicle",
      "identify": [
         {
            "P0": 367,
            "P1": 225,
            "P2": 592,
            "P3": 468
         },
         {
            "P0": 425,
            "P1": 146,
            "P2": 428,
            "P3": 149
         },
         {
            "P0": 414,
            "P1": 146,
            "P2": 422,
            "P3": 149
         },
         {
            "P0": 448,
            "P1": 146,
            "P2": 452,
            "P3": 149
         },
         {
            "P0": 449,
            "P1": 145,
            "P2": 457,
            "P3": 149
         },
         {
            "P0": 22,
            "P1": 286,
            "P2": 209,
            "P3": 1485
         },
         {
            "P0": 668,
            "P1": 154,
            "P2": 707,
            "P3": 166
         },
         {
            "P0": 1386,
            "P1": 154,
            "P2": 1456,
            "P3": 167
         }
      ]
   },
   "object_2": {
      "class": "pedestrian",
      "identify": [
         {
            "P0": 260,
            "P1": 146,
            "P2": 263,
            "P3": 151
         }
      ]
   }
}