{
   "image_name": "399.png",
   "object_1": {
      "class": "vehicle",
      "identify": [
         {
            "P0": 367,
            "P1": 225,
            "P2": 592,
            "P3": 468
         },
         {
            "P0": 1901,
            "P1": 109,
            "P2": 1992,
            "P3": 127
         },
         {
            "P0": 1819,
            "P1": 110,
            "P2": 1908,
            "P3": 128
         },
         {
            "P0": 23,
            "P1": 144,
            "P2": 32,
            "P3": 149
         },
         {
            "P0": 7,
            "P1": 143,
            "P2": 27,
            "P3": 149
         },
         {
            "P0": 18,
            "P1": -10313,
            "P2": 18637,
            "P3": 597
         },
         {
            "P0": 89,
            "P1": 157,
            "P2": 125,
            "P3": 178
         },
         {
            "P0": 1858,
            "P1": 153,
            "P2": 2070,
            "P3": 177
         }
      ]
   },
   "object_2": {
      "class": "pedestrian",
      "identify": []
   }
}